{
  "surfer_id": "20184",
  "name": "Carla Mendez Acebo",
  "country": "Spain",
  "events": [
    {
      "event_id": "4915",
      "event_name": "GADIS Junior Pro Ferrol",
      "location": "Unknown",
      "tour_type": "WJUN",
      "start_date": null,
      "final_position": null,
      "points_earned": null,
      "heats": [
        {
          "heat_id": "heat_92380",
          "round_name": "Round of 40 - Heat 4",
          "position": 3,
          "total_score": 7.84,
          "wave_scores": [
            0.33,
            0.17,
            0.4,
            1.73,
            2.8,
            3.77,
            4.07
          ],
          "advanced": false,
          "heat_date": null
        }
      ]
    }
  ]
}